{"type":"FeatureCollection","features":[{"type":"Feature","geometry":{"type":"Point","coordinates":[-83.082002,42.331906]},"properties":{"cartodb_id":12,"adm0name":"United States of America","name":"LIONS","scalerank":2,"description":"<b><u>Week 17</u></b><br>1/2 - @ Seahawks<br>1:25 PM PST - FOX"}}]}